{
  "source": "demo-seed",
  "matches": [
    {
      "externalId": "demo-cwl-glacier-five-2026-05-26",
      "playedAt": "2026-05-26T20:15:00.000Z",
      "league": "CWL",
      "opponent": "Glacier Five",
      "result": "WIN",
      "side": "BLUE",
      "gameType": "OFFICIAL",
      "source": "demo-seed",
      "notes": "Artificial demo game — safe to delete with npm run clean:demo",
      "participants": [
        {
          "displayName": "Filkus",
          "champion": "Aatrox",
          "side": "BLUE",
          "kills": 3,
          "deaths": 2,
          "assists": 9
        },
        {
          "displayName": "Sentinel",
          "champion": "Jarvan IV",
          "side": "BLUE",
          "kills": 2,
          "deaths": 3,
          "assists": 14
        },
        {
          "displayName": "QuocAnh",
          "champion": "Orianna",
          "side": "BLUE",
          "kills": 7,
          "deaths": 1,
          "assists": 8
        },
        {
          "displayName": "Undertaker",
          "champion": "Jinx",
          "side": "BLUE",
          "kills": 11,
          "deaths": 2,
          "assists": 5
        },
        {
          "displayName": "Limetka",
          "champion": "Thresh",
          "side": "BLUE",
          "kills": 1,
          "deaths": 4,
          "assists": 18
        }
      ],
      "pickBans": [
        { "champion": "Kalista", "type": "BAN", "side": "BLUE", "order": 0 },
        { "champion": "Azir", "type": "BAN", "side": "RED", "order": 1 },
        { "champion": "Lucian", "type": "BAN", "side": "BLUE", "order": 2 },
        { "champion": "Renekton", "type": "BAN", "side": "RED", "order": 3 },
        { "champion": "Maokai", "type": "BAN", "side": "BLUE", "order": 4 },
        { "champion": "Vi", "type": "BAN", "side": "RED", "order": 5 },
        { "champion": "Gnar", "type": "PICK", "side": "RED", "order": 6 },
        { "champion": "Aatrox", "type": "PICK", "side": "BLUE", "order": 7 },
        { "champion": "Jarvan IV", "type": "PICK", "side": "BLUE", "order": 8 },
        { "champion": "Syndra", "type": "PICK", "side": "RED", "order": 9 },
        { "champion": "Orianna", "type": "PICK", "side": "BLUE", "order": 10 },
        { "champion": "Varus", "type": "PICK", "side": "RED", "order": 11 },
        { "champion": "Jinx", "type": "PICK", "side": "BLUE", "order": 12 },
        { "champion": "Nautilus", "type": "PICK", "side": "RED", "order": 13 },
        { "champion": "Thresh", "type": "PICK", "side": "BLUE", "order": 14 },
        { "champion": "Yasuo", "type": "BAN", "side": "RED", "order": 15 },
        { "champion": "Lee Sin", "type": "BAN", "side": "BLUE", "order": 16 }
      ]
    }
  ]
}
